mvt/__init__.py
mvt/android/__init__.py
mvt/android/cli.py
mvt/android/cmd_check_adb.py
mvt/android/cmd_check_androidqf.py
mvt/android/cmd_check_backup.py
mvt/android/cmd_check_bugreport.py
mvt/android/cmd_download_apks.py
mvt/android/utils.py
mvt/android/artifacts/__init__.py
mvt/android/artifacts/artifact.py
mvt/android/artifacts/dumpsys_accessibility.py
mvt/android/artifacts/dumpsys_adb.py
mvt/android/artifacts/dumpsys_appops.py
mvt/android/artifacts/dumpsys_battery_daily.py
mvt/android/artifacts/dumpsys_battery_history.py
mvt/android/artifacts/dumpsys_dbinfo.py
mvt/android/artifacts/dumpsys_package_activities.py
mvt/android/artifacts/dumpsys_packages.py
mvt/android/artifacts/dumpsys_platform_compat.py
mvt/android/artifacts/dumpsys_receivers.py
mvt/android/artifacts/file_timestamps.py
mvt/android/artifacts/getprop.py
mvt/android/artifacts/mounts.py
mvt/android/artifacts/processes.py
mvt/android/artifacts/settings.py
mvt/android/artifacts/tombstone_crashes.py
mvt/android/modules/__init__.py
mvt/android/modules/adb/__init__.py
mvt/android/modules/adb/base.py
mvt/android/modules/adb/chrome_history.py
mvt/android/modules/adb/dumpsys_full.py
mvt/android/modules/adb/files.py
mvt/android/modules/adb/getprop.py
mvt/android/modules/adb/logcat.py
mvt/android/modules/adb/packages.py
mvt/android/modules/adb/processes.py
mvt/android/modules/adb/root_binaries.py
mvt/android/modules/adb/selinux_status.py
mvt/android/modules/adb/settings.py
mvt/android/modules/adb/sms.py
mvt/android/modules/adb/whatsapp.py
mvt/android/modules/androidqf/__init__.py
mvt/android/modules/androidqf/aqf_files.py
mvt/android/modules/androidqf/aqf_getprop.py
mvt/android/modules/androidqf/aqf_log_timestamps.py
mvt/android/modules/androidqf/aqf_packages.py
mvt/android/modules/androidqf/aqf_processes.py
mvt/android/modules/androidqf/aqf_settings.py
mvt/android/modules/androidqf/base.py
mvt/android/modules/androidqf/mounts.py
mvt/android/modules/androidqf/root_binaries.py
mvt-2.7.0.dist-info/licenses/LICENSE
mvt-2.7.0.dist-info/METADATA
mvt-2.7.0.dist-info/WHEEL
mvt-2.7.0.dist-info/entry_points.txt
mvt-2.7.0.dist-info/top_level.txt
mvt-2.7.0.dist-info/RECORD
