Metadata-Version: 2.4
Name: mvt
Version: 2.7.0
Summary: Mobile Verification Toolkit
Author-email: Claudio Guarnieri <nex@nex.sx>
Maintainer-email: Etienne Maynier <tek@randhome.io>, Donncha Ó Cearbhaill <donncha.ocearbhaill@amnesty.org>, Rory Flynn <rory.flynn@amnesty.org>
Project-URL: homepage, https://docs.mvt.re/en/latest/
Project-URL: repository, https://github.com/mvt-project/mvt
Keywords: security,mobile,forensics,malware
Classifier: Development Status :: 5 - Production/Stable
Classifier: Intended Audience :: Information Technology
Classifier: Operating System :: OS Independent
Classifier: Programming Language :: Python
Requires-Python: >=3.10
License-File: LICENSE
Requires-Dist: click==8.3.0
Requires-Dist: rich==14.1.0
Requires-Dist: tld==0.13.1
Requires-Dist: requests==2.32.5
Requires-Dist: simplejson==3.20.2
Requires-Dist: packaging==25.0
Requires-Dist: appdirs==1.4.4
Requires-Dist: iOSbackup==0.9.925
Requires-Dist: adb-shell[usb]==0.4.4
Requires-Dist: libusb1==3.3.1
Requires-Dist: cryptography==46.0.3
Requires-Dist: PyYAML>=6.0.2
Requires-Dist: pyahocorasick==2.2.0
Requires-Dist: betterproto==1.2.5
Requires-Dist: pydantic==2.12.3
Requires-Dist: pydantic-settings==2.10.1
Requires-Dist: NSKeyedUnArchiver==1.5.2
Requires-Dist: python-dateutil==2.9.0.post0
Requires-Dist: tzdata==2025.2
Dynamic: license-file
